{
  "config": {
    "finishVideo": "https://youtu.be/Ybug5lF1tg0",
    "finishLine": [
      [
        502,
        777
      ],
      [
        760,
        736
      ]
    ],
    "starts": {
      "marathon": {
        "time": "05:30:00;00",
        "bibs": [
          240,
          256
        ],
        "startDistance": 65.97
      },
      "fast-half": {
        "time": "06:00:00;00",
        "bibs": [
          160,
          176
        ],
        "startDistance": 129.17
      },
      "half": {
        "time": "08:00:00;00",
        "bibs": [
          0,
          160
        ],
        "startDistance": 129.17
      }
    },
    "lapDistance": 192.37,
    "goals": {
      "marathon": {
        "26_2mi": 219,
        "20mi": 167,
        "13_1mi": 110,
        "10mi": 84,
        "10k": 52,
        "5k": 26
      },
      "half": {
        "13_1mi": 109,
        "10mi": 83,
        "10k": 52,
        "5k": 26
      }
    },
    "directionStarts": [
      "05:30:00",
      "06:00:00",
      "07:00:00",
      "08:00:00",
      "09:00:00",
      "10:00:00"
    ],
    "directions": [
      "CW",
      "CCW",
      "CW",
      "CCW",
      "CW",
      "CCW"
    ],
    "firstLapIsEntrance": true
  },
  "results": [
    {
      "id": 241,
      "name": "Theo Gregersen",
      "lapTimes": [
        16.4,
        50.633,
        53.033,
        53.0,
        53.9,
        53.267,
        55.167,
        53.733,
        51.8,
        52.1,
        52.167,
        53.033,
        53.6,
        52.4,
        52.967,
        51.267,
        51.433,
        52.0,
        52.733,
        52.867,
        52.433,
        52.0,
        52.5,
        52.033,
        52.8,
        52.533,
        53.0,
        51.267,
        52.4,
        53.1,
        53.067,
        52.967,
        52.233,
        53.333,
        52.467,
        58.433,
        52.267,
        52.167,
        52.433,
        52.167,
        51.2,
        52.967,
        51.133,
        52.3,
        51.0,
        49.3,
        51.567,
        52.2,
        52.5,
        52.367,
        52.667,
        54.267,
        53.1,
        51.5,
        51.467,
        52.967,
        51.6,
        52.2,
        52.533,
        52.433,
        52.633,
        52.333,
        51.5,
        53.9,
        53.467,
        52.367,
        51.967,
        51.367,
        52.0,
        51.367,
        52.567,
        53.3,
        53.433,
        52.733,
        52.633,
        51.333,
        52.733,
        52.733,
        53.233,
        52.733,
        53.433,
        52.967,
        53.533,
        50.7,
        52.433,
        53.1,
        52.967,
        52.8,
        53.1,
        52.667,
        51.267,
        51.133,
        51.967,
        52.133,
        51.933,
        51.2,
        52.933,
        52.833,
        52.667,
        52.6,
        52.667,
        52.267,
        52.033,
        52.467,
        56.267,
        51.633,
        51.733,
        51.833,
        52.933,
        52.067,
        50.1,
        51.733,
        52.6,
        52.233,
        52.5,
        53.533,
        53.567,
        51.9,
        51.133,
        51.933,
        52.033,
        51.6,
        52.533,
        52.4,
        52.267,
        52.067,
        52.533,
        52.6,
        53.7,
        52.733,
        53.0,
        52.3,
        52.7,
        52.467,
        52.033,
        52.333,
        52.8,
        52.7,
        52.467,
        52.167,
        52.533,
        54.3,
        53.467,
        52.6,
        53.3,
        53.067,
        52.967,
        53.4,
        52.767,
        54.1,
        54.067,
        52.667,
        53.267,
        53.233,
        53.633,
        53.4,
        53.733,
        53.733,
        53.8,
        53.433,
        54.333,
        54.467,
        54.133,
        54.333,
        53.933,
        54.233,
        54.333,
        55.6,
        56.767,
        58.533,
        57.7,
        57.8,
        59.5,
        57.267,
        58.4,
        57.433,
        59.167,
        60.133,
        59.533,
        59.333,
        60.1,
        61.867,
        61.267,
        60.933,
        61.633,
        62.267,
        61.333,
        62.233,
        62.1,
        63.067,
        63.633,
        65.267,
        65.767,
        66.6,
        65.433,
        62.9,
        62.5,
        65.467,
        65.4,
        66.533,
        66.667,
        65.367,
        66.467,
        66.933,
        68.1,
        67.7,
        67.533,
        67.933,
        68.3,
        69.167,
        69.367,
        68.667,
        68.8,
        67.367,
        70.067,
        69.467,
        68.2,
        66.5,
        64.2,
        60.8,
        58.2
      ]
    },
    {
      "id": 245,
      "name": "Ewin Tang",
      "lapTimes": [
        17.367,
        52.133,
        55.933,
        56.067,
        54.3,
        56.067,
        56.1,
        56.967,
        55.633,
        58.967,
        58.733,
        57.367,
        59.233,
        58.7,
        57.267,
        56.667,
        56.3,
        59.133,
        54.933,
        57.7,
        57.067,
        56.833,
        56.867,
        57.1,
        57.6,
        57.167,
        57.367,
        57.4,
        58.167,
        55.967,
        57.5,
        57.7,
        58.767,
        61.733,
        57.1,
        55.7,
        56.533,
        56.2,
        55.267,
        56.9,
        56.333,
        56.067,
        55.867,
        55.933,
        56.833,
        56.533,
        55.667,
        56.767,
        55.9,
        56.2,
        55.1,
        56.333,
        56.167,
        55.833,
        56.867,
        56.367,
        54.7,
        57.3,
        57.633,
        57.567,
        56.033,
        57.167,
        57.033,
        55.633,
        59.5,
        56.3,
        55.833,
        56.3,
        57.667,
        56.867,
        58.433,
        57.667,
        57.333,
        56.167,
        56.633,
        57.067,
        56.367,
        56.533,
        58.733,
        58.4,
        57.767,
        58.4,
        57.867,
        58.133,
        57.967,
        57.567,
        57.967,
        57.267,
        57.167,
        57.033,
        57.2,
        58.333,
        57.867,
        55.333,
        57.1,
        58.967,
        61.2,
        58.367,
        57.4,
        57.567,
        57.8,
        59.167,
        58.233,
        56.5,
        56.533,
        57.9,
        58.267,
        56.4,
        55.967,
        57.9,
        56.7,
        56.833,
        56.067,
        57.6,
        57.633,
        57.3,
        57.333,
        58.233,
        56.933,
        57.167,
        57.4,
        56.333,
        56.267,
        56.367,
        57.033,
        56.433,
        61.067,
        59.5,
        59.233,
        56.3,
        57.9,
        57.7,
        57.467,
        57.667,
        58.433,
        57.167,
        57.9,
        58.267,
        58.167,
        58.533,
        59.333,
        60.1,
        60.333,
        59.433,
        58.733,
        58.567,
        58.7,
        58.0,
        59.933,
        63.7,
        64.0,
        62.867,
        62.133,
        62.033,
        62.967,
        62.7,
        61.033,
        64.533,
        59.767,
        60.633,
        60.733,
        59.2,
        57.067,
        57.167,
        56.433,
        57.0,
        57.133,
        57.633,
        57.767,
        57.633,
        59.7,
        58.2,
        59.9,
        60.133,
        57.467,
        57.7,
        57.433,
        53.9,
        55.333,
        55.533,
        56.167,
        57.033,
        59.2,
        58.333,
        59.933,
        60.767,
        61.5,
        65.767,
        62.867,
        62.267,
        62.233,
        61.0,
        77.067,
        62.867,
        63.6,
        64.267,
        64.4,
        65.367,
        66.633,
        68.867,
        68.667,
        71.933,
        72.6,
        73.933,
        71.167,
        72.133,
        71.533,
        70.533,
        70.567,
        67.533,
        68.367,
        70.367,
        72.9,
        76.1,
        84.967,
        79.0,
        79.8,
        75.5,
        64.667,
        61.333,
        109.4
      ]
    },
    {
      "id": 243,
      "name": "Benjamin Han",
      "lapTimes": [
        19.033,
        57.3,
        59.3,
        58.467,
        59.5,
        59.867,
        60.5,
        59.7,
        60.267,
        59.933,
        59.6,
        59.367,
        60.7,
        59.833,
        60.333,
        59.5,
        59.467,
        59.833,
        58.467,
        57.633,
        58.1,
        57.667,
        57.533,
        57.5,
        57.533,
        57.733,
        57.3,
        58.2,
        56.233,
        57.3,
        57.6,
        58.9,
        61.667,
        57.133,
        55.833,
        56.1,
        56.5,
        55.467,
        56.7,
        56.433,
        55.967,
        55.267,
        55.8,
        55.767,
        55.567,
        56.1,
        56.3,
        56.0,
        55.433,
        55.567,
        56.067,
        55.633,
        55.3,
        56.533,
        56.4,
        55.6,
        56.833,
        56.1,
        56.467,
        55.733,
        56.167,
        55.267,
        56.5,
        56.433,
        55.833,
        57.133,
        56.267,
        57.233,
        57.2,
        56.233,
        57.233,
        58.833,
        57.867,
        55.467,
        55.8,
        56.1,
        56.2,
        57.367,
        58.333,
        56.367,
        57.467,
        58.767,
        57.367,
        56.467,
        56.767,
        56.333,
        57.367,
        57.3,
        59.767,
        57.867,
        58.133,
        57.133,
        58.0,
        57.4,
        57.533,
        63.333,
        58.3,
        60.333,
        58.333,
        59.333,
        59.567,
        59.567,
        59.7,
        58.733,
        60.1,
        59.067,
        59.433,
        59.367,
        60.067,
        59.1,
        59.267,
        59.2,
        59.233,
        58.967,
        58.567,
        59.5,
        59.433,
        56.933,
        58.433,
        57.8,
        59.967,
        61.667,
        59.933,
        59.467,
        58.9,
        58.7,
        58.533,
        58.6,
        59.267,
        60.2,
        58.833,
        57.7,
        58.2,
        58.8,
        59.767,
        59.933,
        58.0,
        59.267,
        59.167,
        60.433,
        60.2,
        60.433,
        60.2,
        60.733,
        59.9,
        61.3,
        89.333,
        64.5,
        66.0,
        65.3,
        64.967,
        63.933,
        64.7,
        63.867,
        61.133,
        68.633,
        63.267,
        63.867,
        66.067,
        65.167,
        65.1,
        64.167,
        60.567,
        59.967,
        60.267,
        58.7,
        90.967,
        95.167,
        121.333,
        78.2,
        80.8,
        64.0,
        64.033,
        64.433,
        63.8,
        63.433,
        61.133,
        61.367,
        60.6,
        61.0,
        60.4,
        60.8,
        61.067,
        61.633,
        61.567,
        61.3,
        61.467,
        63.133,
        62.4,
        90.5,
        62.567,
        62.733,
        61.8,
        61.167,
        62.7,
        60.367,
        60.233,
        60.667,
        60.6,
        61.2,
        59.5,
        60.067,
        59.567,
        87.267,
        72.833,
        65.567,
        64.767,
        64.5,
        65.433,
        69.0,
        65.867,
        65.1,
        68.033,
        67.733,
        68.067,
        64.867,
        66.967,
        66.3,
        62.967,
        61.033
      ]
    },
    {
      "id": 240,
      "name": "Yuqian Jiang",
      "lapTimes": [
        80.267,
        59.967,
        59.967,
        60.133,
        60.733,
        60.633,
        60.1,
        60.633,
        60.3,
        60.2,
        59.9,
        59.567,
        59.8,
        60.033,
        59.733,
        60.0,
        60.9,
        60.033,
        60.2,
        59.567,
        60.567,
        59.7,
        60.233,
        60.533,
        59.933,
        60.433,
        59.933,
        60.4,
        60.1,
        60.3,
        60.867,
        60.0,
        59.4,
        59.5,
        59.8,
        60.467,
        61.3,
        64.567,
        61.033,
        60.8,
        59.533,
        59.867,
        61.0,
        61.533,
        61.467,
        61.533,
        62.6,
        60.467,
        59.833,
        61.0,
        60.033,
        60.467,
        59.133,
        60.633,
        61.9,
        61.1,
        60.533,
        61.6,
        61.7,
        62.067,
        61.967,
        61.533,
        63.067,
        63.067,
        62.4,
        61.333,
        62.167,
        62.233,
        61.2,
        61.933,
        61.733,
        61.9,
        60.733,
        60.6,
        62.733,
        62.133,
        62.033,
        64.533,
        61.6,
        61.833,
        61.567,
        62.0,
        61.2,
        61.167,
        61.2,
        61.667,
        62.0,
        61.833,
        62.467,
        64.8,
        62.567,
        62.8,
        62.367,
        62.233,
        62.567,
        73.5,
        63.333,
        62.933,
        61.267,
        61.3,
        64.433,
        64.933,
        62.3,
        62.333,
        62.0,
        62.4,
        62.8,
        62.967,
        62.5,
        63.967,
        63.967,
        68.433,
        68.167,
        65.3,
        65.767,
        66.333,
        66.5,
        65.3,
        71.233,
        70.533,
        66.7,
        66.167,
        64.4,
        64.2,
        65.967,
        65.9,
        66.5,
        68.133,
        66.767,
        66.6,
        69.0,
        67.0,
        72.133,
        75.4,
        69.833,
        67.733,
        67.9,
        67.267,
        68.4,
        68.267,
        67.967,
        68.167,
        67.967,
        72.6,
        69.167,
        73.8,
        73.9,
        71.733,
        68.767,
        69.533,
        75.933,
        74.5,
        72.467,
        68.8,
        67.267,
        66.8,
        67.433,
        66.967,
        69.7,
        70.167,
        69.567,
        70.367,
        73.5,
        72.167,
        71.633,
        72.333,
        71.667,
        81.567,
        125.367,
        76.367,
        76.5,
        74.967,
        143.433,
        146.6,
        79.533,
        74.567,
        71.667,
        72.233,
        72.667,
        71.367,
        70.433,
        69.567,
        71.8,
        70.8,
        68.433,
        70.433,
        69.1,
        67.933,
        69.4,
        68.6,
        71.967,
        71.533,
        68.533,
        69.2,
        66.6,
        67.433,
        67.567,
        68.6,
        70.4,
        67.467,
        66.667,
        66.8,
        66.9,
        66.267,
        66.233,
        67.1,
        67.767,
        68.733,
        68.167,
        67.233,
        73.933,
        73.133,
        70.833,
        67.9,
        69.8,
        68.7,
        69.8,
        70.0,
        68.933,
        68.7,
        71.233
      ]
    },
    {
      "id": 162,
      "name": "Joe Cutler",
      "lapTimes": [
        40.467,
        55.667,
        47.533,
        49.2,
        50.067,
        50.2,
        48.833,
        48.4,
        47.8,
        48.4,
        48.367,
        48.567,
        48.3,
        48.267,
        49.567,
        48.233,
        48.533,
        48.167,
        48.333,
        47.733,
        48.233,
        47.5,
        47.7,
        48.0,
        47.533,
        47.8,
        48.6,
        48.1,
        48.533,
        48.733,
        48.933,
        48.333,
        48.533,
        48.233,
        49.133,
        49.667,
        48.9,
        49.567,
        49.633,
        48.3,
        47.333,
        47.333,
        46.967,
        48.4,
        48.233,
        48.267,
        47.933,
        47.833,
        47.233,
        48.0,
        47.333,
        47.267,
        47.5,
        47.5,
        47.1,
        47.467,
        47.367,
        47.233,
        47.233,
        47.967,
        47.867,
        47.433,
        48.233,
        47.3,
        46.9,
        47.7,
        47.533,
        47.0,
        47.067,
        47.3,
        47.333,
        46.767,
        46.367,
        46.9,
        47.567,
        52.233,
        47.833,
        45.9,
        46.333,
        46.833,
        47.2,
        46.533,
        45.933,
        46.067,
        46.267,
        46.767,
        46.133,
        47.0,
        48.067,
        46.433,
        46.167,
        47.433,
        47.1,
        47.4,
        46.933,
        46.267,
        46.533,
        47.533,
        47.0,
        47.133,
        47.433,
        47.2,
        47.367,
        47.5,
        46.9,
        46.933,
        47.133,
        46.767,
        46.667,
        46.633,
        46.3
      ]
    },
    {
      "id": 161,
      "name": "Nick Walker",
      "lapTimes": [
        41.267,
        54.8,
        47.233,
        49.167,
        50.033,
        50.2,
        48.867,
        48.467,
        47.8,
        48.4,
        48.3,
        48.633,
        48.533,
        47.967,
        49.533,
        48.4,
        48.433,
        48.167,
        48.333,
        47.833,
        48.167,
        47.467,
        47.667,
        48.367,
        47.2,
        47.833,
        48.633,
        47.967,
        48.7,
        48.8,
        49.1,
        48.7,
        48.6,
        48.167,
        49.133,
        49.667,
        48.9,
        49.6,
        49.667,
        48.533,
        47.067,
        47.367,
        46.967,
        48.3,
        48.233,
        48.367,
        47.9,
        47.867,
        47.3,
        47.9,
        47.4,
        47.333,
        47.7,
        47.3,
        47.067,
        47.4,
        47.3,
        47.267,
        47.233,
        47.967,
        47.867,
        47.367,
        48.3,
        47.3,
        46.833,
        47.7,
        47.633,
        46.967,
        47.033,
        47.5,
        47.233,
        46.7,
        46.533,
        46.8,
        47.8,
        51.333,
        47.767,
        45.8,
        46.367,
        46.867,
        47.133,
        47.567,
        45.667,
        46.267,
        46.133,
        46.667,
        46.133,
        46.933,
        48.167,
        46.333,
        46.467,
        47.233,
        47.133,
        47.367,
        46.967,
        46.467,
        46.6,
        47.3,
        47.067,
        47.067,
        47.667,
        46.867,
        47.333,
        47.533,
        47.0,
        47.1,
        47.133,
        46.667,
        46.4,
        46.433,
        46.3
      ]
    },
    {
      "id": 160,
      "name": "Olivia Harris",
      "lapTimes": [
        41.5,
        55.3,
        53.667,
        54.233,
        54.2,
        55.033,
        54.7,
        54.267,
        54.267,
        54.467,
        53.933,
        54.6,
        54.967,
        54.933,
        54.833,
        56.0,
        55.6,
        54.967,
        54.633,
        55.1,
        55.633,
        56.433,
        56.233,
        56.6,
        56.533,
        56.7,
        56.3,
        57.267,
        56.733,
        56.667,
        56.8,
        56.967,
        57.767,
        57.133,
        57.0,
        56.833,
        56.3,
        56.433,
        55.833,
        55.9,
        56.667,
        55.9,
        56.533,
        55.733,
        56.0,
        56.567,
        56.133,
        56.167,
        55.833,
        56.467,
        56.3,
        56.067,
        55.533,
        55.433,
        55.567,
        55.2,
        54.8,
        55.233,
        54.667,
        53.833,
        54.4,
        54.3,
        54.7,
        54.867,
        56.1,
        60.0,
        55.467,
        55.067,
        55.1,
        55.033,
        54.9,
        53.733,
        53.7,
        53.8,
        54.567,
        53.6,
        54.5,
        53.767,
        54.6,
        53.767,
        54.633,
        54.133,
        53.867,
        54.0,
        53.633,
        53.933,
        53.233,
        53.667,
        54.267,
        53.633,
        52.633,
        53.133,
        52.167,
        53.6,
        53.867,
        53.3,
        52.7,
        52.367,
        52.733,
        53.0,
        52.5,
        52.667,
        52.9,
        53.033,
        52.933,
        52.633,
        52.5,
        53.767,
        53.9,
        50.867,
        47.933
      ]
    },
    {
      "id": 26,
      "name": "James Yoo",
      "lapTimes": [
        28.233,
        52.1,
        54.4,
        56.433,
        56.767,
        56.967,
        56.0,
        56.5,
        53.0,
        56.467,
        57.633,
        56.8,
        56.7,
        58.9,
        56.467,
        56.4,
        58.5,
        59.833,
        59.067,
        58.167,
        57.867,
        57.267,
        56.933,
        59.667,
        62.0,
        61.733,
        62.233,
        62.467,
        61.167,
        60.633,
        57.733,
        59.733,
        62.267,
        60.633,
        60.9,
        60.033,
        59.4,
        59.767,
        60.2,
        59.767,
        61.267,
        60.567,
        59.267,
        59.867,
        60.367,
        61.533,
        60.2,
        61.067,
        61.467,
        61.167,
        61.1,
        61.9,
        62.2,
        63.233,
        63.967,
        61.967,
        63.333,
        61.7,
        64.133,
        64.1,
        64.0,
        66.933,
        60.467,
        60.367,
        61.833,
        60.733,
        61.533,
        60.467,
        62.067,
        62.333,
        62.633,
        62.533,
        63.4,
        64.0,
        62.767,
        62.767,
        63.033,
        62.033,
        62.533,
        63.867,
        64.0,
        64.433,
        64.133,
        63.3,
        63.833,
        64.167,
        64.533,
        63.667,
        63.167,
        62.333,
        65.333,
        64.733,
        64.9,
        64.5,
        65.1,
        64.033,
        62.933,
        65.833,
        64.567,
        63.8,
        62.567,
        64.467,
        63.2,
        63.867,
        63.233,
        63.7,
        63.367,
        63.967,
        63.467,
        62.367,
        63.0,
        62.233,
        64.3,
        44.767,
        212.133
      ]
    },
    {
      "id": 1,
      "name": "Margaret Li",
      "lapTimes": [
        29.567,
        59.367,
        64.1,
        63.467,
        64.4,
        64.233,
        65.467,
        65.067,
        65.0,
        63.667,
        63.467,
        64.5,
        69.367,
        66.067,
        65.9,
        66.033,
        65.733,
        67.233,
        66.667,
        67.5,
        69.333,
        65.1,
        64.933,
        65.333,
        65.5,
        65.433,
        65.1,
        64.767,
        65.567,
        64.367,
        64.867,
        65.667,
        64.833,
        67.1,
        66.667,
        65.8,
        66.133,
        66.067,
        67.5,
        68.767,
        67.2,
        70.9,
        68.467,
        67.767,
        67.2,
        67.7,
        69.733,
        67.133,
        68.7,
        67.267,
        67.167,
        68.233,
        70.467,
        68.4,
        67.833,
        71.867,
        69.267,
        69.033,
        69.9,
        70.7,
        70.3,
        104.567,
        69.033,
        70.833,
        71.133,
        72.133,
        72.467,
        69.567,
        70.4,
        72.067,
        73.267,
        71.0,
        71.333,
        70.167,
        71.033,
        70.567,
        72.333,
        72.667,
        72.033,
        74.2,
        73.867,
        73.333,
        70.9,
        71.567,
        72.567,
        72.867,
        72.0,
        71.567,
        71.967,
        71.633,
        71.467,
        72.933,
        73.767,
        77.633,
        135.9,
        76.533,
        69.233,
        71.4,
        90.533,
        74.433,
        73.567,
        73.833,
        72.233,
        74.467,
        75.867,
        72.0,
        72.7,
        74.067,
        73.233,
        50.6,
        156.6,
        146.267
      ]
    },
    {
      "id": 3,
      "name": "Ryan Zambrotta",
      "lapTimes": [
        30.3,
        56.067,
        57.633,
        57.8,
        58.9,
        56.733,
        56.067,
        56.9,
        55.5,
        54.367,
        54.167,
        54.4,
        55.867,
        53.967,
        55.367,
        55.867,
        55.767,
        54.867,
        54.233,
        56.033,
        55.2,
        55.633,
        55.067,
        55.833,
        57.7,
        57.033,
        54.567,
        55.867,
        56.0,
        56.833,
        56.933,
        58.367,
        58.933,
        56.533,
        56.033,
        57.433,
        57.7,
        55.633,
        56.567,
        54.567,
        54.833,
        54.7,
        55.933,
        57.2,
        56.933,
        55.667,
        58.867,
        59.467,
        60.267,
        60.667,
        60.567,
        58.933,
        59.267,
        58.867,
        59.533,
        59.167,
        58.7,
        59.367,
        58.533,
        59.2,
        60.033,
        58.9,
        60.033,
        61.033,
        68.733,
        62.2,
        60.567,
        59.867,
        59.533,
        59.9,
        60.3,
        59.633,
        59.7,
        60.5,
        60.467,
        61.033,
        61.3,
        64.433,
        116.267,
        58.167,
        59.267,
        61.0,
        65.6,
        64.833,
        65.8,
        63.6,
        65.5,
        67.467,
        66.367,
        65.867,
        66.833,
        67.7,
        69.0,
        70.367,
        71.767,
        83.067,
        70.033,
        68.733,
        70.767,
        89.433,
        119.167,
        68.7,
        74.5,
        75.733,
        76.867,
        128.967,
        86.833,
        95.233,
        62.1,
        98.8
      ]
    },
    {
      "id": 46,
      "name": "Mike Merrill",
      "lapTimes": [
        32.667,
        54.933,
        59.467,
        60.567,
        60.833,
        60.633,
        61.3,
        61.167,
        63.067,
        62.167,
        61.833,
        63.2,
        61.833,
        63.8,
        62.467,
        63.433,
        61.933,
        63.133,
        62.967,
        63.367,
        64.933,
        65.2,
        63.0,
        62.9,
        64.3,
        63.7,
        63.933,
        64.0,
        65.067,
        66.7,
        74.867,
        65.133,
        66.633,
        62.767,
        64.333,
        62.667,
        62.733,
        64.433,
        90.167,
        59.767,
        64.067,
        62.633,
        63.667,
        63.0,
        63.433,
        62.0,
        63.8,
        63.7,
        63.867,
        63.633,
        63.1,
        64.467,
        64.533,
        64.233,
        63.933,
        62.933,
        64.833,
        66.733,
        63.533,
        64.433,
        64.0,
        80.733,
        83.7,
        64.567,
        63.567,
        63.033,
        63.1,
        64.767,
        64.667,
        66.067,
        66.167,
        67.733,
        73.933,
        69.5,
        68.2,
        70.7,
        95.833,
        71.1,
        70.367,
        72.5,
        72.6,
        146.367,
        73.8,
        73.267,
        65.533,
        66.833,
        70.3,
        71.267,
        74.933,
        101.2,
        156.167,
        113.267,
        75.733,
        72.5,
        67.1,
        66.833,
        66.533,
        68.2,
        67.2,
        69.8,
        72.567,
        72.767,
        70.8,
        65.433,
        70.167,
        68.9,
        55.833,
        41.733,
        612.933
      ]
    },
    {
      "id": 2,
      "name": "Hannah Lee",
      "lapTimes": [
        32.667,
        58.0,
        62.433,
        56.767,
        57.567,
        57.233,
        57.433,
        57.567,
        58.767,
        56.633,
        57.2,
        57.2,
        58.167,
        57.933,
        57.6,
        59.033,
        58.1,
        57.733,
        58.867,
        58.967,
        59.167,
        58.767,
        57.667,
        58.3,
        59.633,
        60.533,
        59.833,
        58.033,
        59.0,
        59.667,
        57.767,
        59.133,
        58.933,
        58.367,
        58.3,
        57.667,
        58.7,
        59.2,
        58.933,
        59.8,
        58.6,
        59.533,
        59.167,
        59.7,
        61.333,
        59.6,
        59.733,
        61.233,
        59.867,
        57.567,
        57.8,
        59.167,
        60.667,
        57.933,
        59.5,
        57.733,
        60.267,
        58.6,
        60.633,
        58.367,
        58.167,
        58.167,
        60.333,
        57.2,
        57.533,
        58.0,
        58.867,
        56.333,
        56.967,
        57.6,
        58.0,
        55.833,
        57.333,
        58.1,
        58.067,
        57.0,
        57.833,
        58.867,
        59.233,
        57.967,
        57.7,
        57.233,
        58.2,
        58.433,
        57.9,
        56.433,
        56.8,
        57.067,
        56.7,
        58.367,
        57.667,
        57.033,
        56.333,
        56.2,
        59.433,
        59.833,
        58.9,
        58.167,
        57.567,
        58.367,
        59.7,
        57.067,
        59.067,
        59.2,
        59.133,
        59.233,
        57.933,
        61.3,
        59.467,
        56.567,
        164.567
      ]
    },
    {
      "id": 8,
      "name": "Ellis Michael",
      "lapTimes": [
        32.867,
        57.533,
        62.833,
        56.533,
        57.7,
        57.2,
        61.1,
        53.7,
        58.967,
        56.4,
        57.167,
        57.133,
        58.3,
        57.933,
        57.833,
        59.433,
        58.167,
        69.8,
        46.933,
        58.9,
        59.0,
        58.667,
        58.0,
        57.833,
        59.767,
        60.4,
        59.767,
        58.033,
        58.633,
        59.633,
        57.967,
        60.7,
        57.467,
        59.1,
        57.233,
        58.0,
        58.533,
        59.5,
        58.667,
        60.367,
        60.1,
        57.933,
        59.033,
        59.7,
        60.9,
        59.767,
        60.333,
        60.867,
        59.733,
        57.533,
        57.867,
        59.1,
        60.6,
        58.067,
        59.567,
        57.667,
        60.267,
        59.033,
        60.133,
        58.6,
        58.1,
        58.567,
        59.7,
        57.267,
        57.5,
        58.4,
        57.933,
        56.9,
        56.967,
        57.733,
        57.833,
        55.833,
        57.067,
        58.167,
        58.333,
        56.933,
        57.833,
        59.267,
        58.967,
        57.867,
        57.733,
        57.1,
        58.3,
        58.433,
        57.867,
        56.433,
        56.667,
        57.067,
        56.967,
        58.233,
        57.633,
        56.933,
        56.067,
        55.9,
        59.333,
        60.233,
        58.867,
        58.0,
        57.3,
        59.267,
        59.033,
        56.567,
        59.633,
        59.1,
        58.767,
        59.0,
        59.367,
        61.3,
        61.3,
        57.033,
        69.267
      ]
    },
    {
      "id": 21,
      "name": "Dale Berg",
      "lapTimes": [
        33.333,
        56.567,
        53.333,
        55.2,
        57.6,
        54.567,
        54.967,
        55.7,
        56.467,
        57.133,
        57.6,
        54.433,
        60.167,
        60.167,
        58.1,
        56.733,
        57.667,
        61.367,
        59.8,
        59.8,
        59.067,
        58.033,
        58.3,
        60.7,
        59.3,
        58.167,
        58.667,
        59.533,
        62.8,
        58.5,
        58.933,
        60.233,
        58.667,
        57.133,
        57.8,
        57.7,
        57.667,
        60.033,
        53.0,
        58.4,
        59.7,
        57.433,
        58.133,
        56.4,
        58.633,
        61.0,
        58.9,
        58.867,
        60.233,
        58.733,
        60.533,
        59.5,
        60.233,
        58.7,
        56.767,
        58.433,
        58.667,
        60.5,
        62.2,
        59.1,
        57.4,
        59.567,
        61.5,
        59.833,
        57.167,
        58.767,
        55.833,
        54.267,
        55.633,
        54.6,
        55.867,
        56.4,
        57.467,
        56.6,
        55.833,
        55.167,
        54.667,
        57.3,
        66.167,
        58.267,
        56.833,
        58.0,
        56.833,
        65.333,
        57.433,
        57.133,
        55.433,
        54.833,
        55.6,
        55.167,
        54.933,
        56.467,
        55.667,
        53.167,
        53.067,
        50.7,
        52.967,
        55.067,
        55.567,
        55.2,
        54.1,
        56.2,
        54.2,
        54.8,
        55.5,
        54.533,
        56.6,
        55.9,
        57.0,
        57.833,
        58.733,
        58.933,
        58.067,
        51.8
      ]
    },
    {
      "id": 35,
      "name": "Ben Sherman",
      "lapTimes": [
        33.333,
        52.0,
        52.467,
        55.233,
        55.333,
        53.567,
        53.667,
        54.067,
        54.967,
        53.4,
        54.4,
        53.733,
        54.0,
        54.0,
        53.967,
        52.5,
        52.567,
        54.767,
        55.5,
        55.433,
        55.967,
        56.767,
        55.6,
        56.9,
        56.567,
        57.3,
        55.133,
        57.467,
        57.767,
        56.533,
        56.533,
        58.633,
        57.667,
        57.767,
        57.967,
        57.467,
        60.767,
        57.767,
        59.367,
        57.967,
        57.5,
        57.633,
        56.7,
        58.2,
        58.5,
        57.733,
        59.8,
        59.533,
        58.833,
        56.667,
        55.233,
        50.967
      ]
    },
    {
      "id": 6,
      "name": "Chandrakana Nandi",
      "lapTimes": [
        33.767,
        57.433,
        61.967,
        57.967,
        57.3,
        57.467,
        58.433,
        57.2,
        58.133,
        58.667,
        56.767,
        57.233,
        56.667,
        56.8,
        58.0,
        59.1,
        58.267,
        57.033,
        59.1,
        59.267,
        60.033,
        58.2,
        58.033,
        58.8,
        58.7,
        60.467,
        59.5,
        58.267,
        59.567,
        60.4,
        59.067,
        58.7,
        58.033,
        59.833,
        58.333,
        59.533,
        59.333,
        58.3,
        60.333,
        60.667,
        59.1,
        59.4,
        60.433,
        59.4,
        58.967,
        59.867,
        60.667,
        61.533,
        60.467,
        61.133,
        60.533,
        60.267,
        60.9,
        61.533,
        63.167,
        61.9,
        63.1,
        62.2,
        63.567,
        63.733,
        65.067,
        67.233,
        65.033,
        64.233,
        63.833,
        62.233,
        61.867,
        63.0,
        63.1,
        62.667,
        61.567,
        62.567,
        63.133,
        58.833,
        63.2,
        62.433,
        63.2,
        62.5,
        62.867,
        62.233,
        62.667,
        61.7,
        63.4,
        61.567,
        61.167,
        61.3,
        59.9,
        62.5,
        60.267,
        60.2,
        60.467,
        60.833,
        60.133,
        61.167,
        60.767,
        61.3,
        62.3,
        62.3,
        63.2,
        63.467,
        62.133,
        62.667,
        63.1,
        62.267,
        62.267,
        60.333,
        62.4,
        63.2,
        62.467,
        63.367,
        63.333,
        63.333
      ]
    },
    {
      "id": 20,
      "name": "Chinmay Nirkhe",
      "lapTimes": [
        34.367,
        55.067,
        59.867,
        58.567,
        59.167,
        57.467,
        56.233,
        56.867,
        55.2,
        56.567,
        53.733,
        52.6,
        53.567,
        55.8,
        57.033,
        57.0,
        56.0,
        56.4,
        54.633,
        56.733,
        53.033,
        54.167,
        51.867,
        53.133,
        56.067,
        58.567,
        58.667,
        59.4,
        61.233,
        61.667,
        57.2,
        57.767,
        59.1,
        58.7,
        59.533,
        57.533,
        58.367,
        59.0,
        58.433,
        58.767,
        58.767,
        58.967,
        59.8,
        59.6,
        59.567,
        60.867,
        59.333,
        60.133,
        60.767,
        60.5,
        58.9,
        59.267,
        58.4,
        58.367,
        58.167,
        58.533,
        57.667,
        60.233,
        59.867,
        59.933,
        58.133,
        58.2,
        59.633,
        61.067,
        55.333,
        57.7,
        59.5,
        57.867,
        57.833,
        58.4,
        58.267,
        59.267,
        58.367,
        57.767,
        57.467,
        57.367,
        57.267,
        60.067,
        59.833,
        60.267,
        61.833,
        61.6,
        62.467,
        61.967,
        63.467,
        63.1,
        62.233,
        62.4,
        63.133,
        62.533,
        62.767,
        62.7,
        62.867,
        64.433,
        64.967,
        63.833,
        63.533,
        63.167,
        63.733,
        64.8,
        62.667,
        61.767,
        63.333,
        63.5,
        63.667,
        65.033,
        62.567,
        58.967,
        57.733,
        42.033
      ]
    },
    {
      "id": 19,
      "name": "Alan Min",
      "lapTimes": [
        34.4,
        57.9,
        62.833,
        63.333,
        128.2,
        64.867,
        65.3,
        66.0,
        66.133,
        67.667,
        68.8,
        67.333,
        67.167,
        68.4,
        68.667,
        66.167,
        67.733,
        68.067,
        68.533,
        69.067,
        72.267,
        67.1,
        67.433,
        70.2,
        69.7,
        68.8,
        69.667,
        68.933,
        70.833,
        73.633,
        71.033,
        69.267,
        69.633,
        70.967,
        71.333,
        71.167,
        71.067,
        70.567,
        72.9,
        73.133,
        76.233,
        74.467,
        74.5,
        75.7,
        76.533,
        75.833,
        74.767,
        77.2,
        74.9,
        76.067,
        75.467,
        73.933,
        142.867,
        151.633,
        137.7,
        67.9,
        68.133,
        71.033,
        69.8,
        73.4,
        73.333,
        73.833,
        75.167,
        77.567,
        76.767,
        73.067,
        119.033,
        140.8,
        67.4,
        72.533,
        71.3,
        76.4,
        77.1,
        78.0,
        76.667,
        138.7,
        71.433,
        74.133,
        74.167,
        73.167,
        76.4,
        116.9,
        131.733,
        68.467,
        74.867,
        74.533,
        73.0,
        77.3,
        111.033,
        138.5,
        70.7,
        73.5,
        99.4,
        135.9,
        66.8,
        75.933,
        81.167,
        118.667,
        80.467,
        103.833,
        79.567,
        117.967,
        74.867,
        103.4,
        90.167,
        96.433,
        101.0,
        88.9,
        128.067,
        69.733,
        117.567,
        63.633
      ]
    },
    {
      "id": 4,
      "name": "Zachary Tatlock",
      "lapTimes": [
        35.367,
        57.0,
        61.133,
        57.233,
        57.2,
        57.167,
        57.367,
        57.333,
        57.667,
        57.1,
        57.333,
        57.2,
        58.433,
        57.567,
        57.967,
        59.167,
        58.133,
        57.667,
        59.1,
        58.767,
        59.133,
        58.833,
        57.8,
        59.4,
        59.167,
        60.133,
        59.3,
        58.3,
        59.133,
        59.333,
        58.933,
        58.3,
        58.7,
        58.833,
        58.3,
        58.267,
        58.167,
        59.2,
        59.033,
        59.0,
        58.933,
        60.0,
        59.6,
        59.5,
        60.9,
        59.4,
        61.333,
        60.3,
        60.7,
        58.833,
        59.3,
        58.833,
        59.7,
        59.0,
        58.767,
        58.633,
        58.5,
        59.9,
        59.3,
        59.933,
        59.3,
        61.167,
        69.233,
        62.433,
        60.3,
        59.533,
        59.733,
        59.8,
        59.9,
        60.0,
        59.767,
        60.367,
        60.433,
        61.167,
        60.667,
        61.433,
        61.667,
        62.967,
        62.0,
        62.5,
        62.967,
        61.567,
        61.267,
        60.333,
        59.533,
        59.933,
        59.167,
        59.933,
        60.367,
        60.767,
        60.7,
        60.833,
        62.1,
        63.067,
        62.267,
        61.5,
        64.4,
        61.9,
        63.967,
        62.233,
        62.833,
        63.533,
        64.2,
        63.967,
        63.267,
        62.333,
        62.7,
        61.667,
        62.7,
        57.3,
        79.8,
        138.933,
        145.733
      ]
    },
    {
      "id": 33,
      "name": "Dhruba Ghosh",
      "lapTimes": [
        36.267,
        60.467,
        61.167,
        65.0,
        64.8,
        62.967,
        62.467,
        62.433,
        62.3,
        61.567,
        61.133,
        67.467,
        76.8,
        71.667,
        69.0,
        67.933,
        65.0,
        63.033,
        63.5,
        64.667,
        65.233,
        62.433,
        63.067,
        62.567,
        62.933,
        62.167,
        61.567,
        69.933,
        69.733,
        62.833,
        62.167,
        64.567,
        63.433,
        63.267,
        64.9,
        61.767,
        61.833,
        62.033,
        62.967,
        62.033,
        60.567,
        62.233,
        60.1,
        62.433,
        62.633,
        62.133,
        62.933,
        63.333,
        63.3,
        62.867,
        61.033,
        63.067,
        62.767,
        61.7,
        64.433,
        64.3,
        66.2,
        68.933,
        63.233,
        65.233,
        66.2,
        68.833,
        66.8,
        64.633,
        63.6,
        63.8,
        64.267,
        64.533,
        61.7,
        62.733,
        63.933,
        65.033,
        62.3,
        62.267,
        64.533,
        62.3,
        61.767,
        62.467,
        62.8,
        62.1,
        61.933,
        61.067,
        63.567,
        63.433,
        61.5,
        63.233,
        61.6,
        60.667,
        62.167,
        60.9,
        59.967,
        60.233,
        59.667,
        60.833,
        62.067,
        60.9,
        59.633,
        59.433,
        60.167,
        59.767,
        58.067,
        57.667,
        57.6,
        57.233,
        56.333,
        57.2,
        57.9,
        57.7,
        55.367,
        49.6
      ]
    },
    {
      "id": 38,
      "name": "Henri Fung",
      "lapTimes": [
        37.1,
        62.467,
        63.5,
        66.433,
        68.433,
        68.833,
        64.933,
        67.233,
        64.667,
        68.167,
        69.533,
        68.4,
        72.2,
        69.967,
        70.6,
        73.133,
        72.633,
        71.933,
        67.367,
        65.7,
        67.6,
        68.033,
        70.8,
        73.267,
        72.5,
        73.133,
        73.7,
        72.933,
        74.633,
        74.4,
        75.2,
        76.267,
        76.833,
        75.133,
        74.667,
        76.333,
        74.967,
        71.6,
        70.7,
        72.867,
        73.833,
        74.533,
        73.567,
        73.3,
        72.933,
        73.067,
        74.9,
        73.967,
        75.867,
        78.067,
        78.5,
        82.767,
        77.467,
        79.267,
        79.133,
        78.667,
        75.633,
        79.433,
        77.633,
        77.533,
        80.5,
        81.267,
        80.767,
        83.133,
        81.767,
        84.8,
        86.167,
        84.9,
        86.0,
        83.3,
        86.2,
        88.333,
        89.3,
        92.2,
        95.333,
        94.2,
        94.367,
        91.967,
        93.433,
        97.567,
        202.7,
        79.1,
        88.9,
        91.433,
        95.4,
        98.933,
        119.733,
        92.467,
        92.133,
        122.567,
        103.333,
        90.967,
        104.767,
        94.1,
        104.4,
        82.633,
        96.333,
        73.3,
        117.033,
        146.933,
        68.0,
        95.867,
        102.233,
        98.367,
        95.967,
        110.767,
        116.967,
        85.467,
        108.167,
        101.3
      ]
    },
    {
      "id": 13,
      "name": "Anshul Nasery",
      "lapTimes": [
        38.733,
        58.867,
        60.3,
        62.833,
        62.233,
        64.333,
        65.833,
        66.133,
        63.3,
        63.167,
        62.8,
        64.767,
        69.733,
        65.233,
        65.667,
        66.633,
        65.267,
        65.367,
        66.133,
        63.167,
        63.567,
        65.567,
        68.7,
        65.733,
        63.133,
        67.167,
        65.133,
        64.033,
        66.0,
        63.267,
        65.267,
        63.3,
        63.967,
        62.567,
        66.0,
        65.133,
        66.833,
        65.9,
        65.533,
        63.633,
        64.233,
        63.667,
        65.3,
        65.267,
        64.367,
        64.3,
        67.067,
        62.833,
        63.767,
        62.9,
        63.533,
        63.867,
        64.0,
        66.9,
        63.233,
        64.167,
        64.367,
        70.433,
        65.033,
        65.033,
        63.7,
        66.567,
        65.433,
        67.367,
        65.4,
        64.433,
        66.1,
        65.8,
        66.3,
        66.7,
        66.333,
        66.467,
        65.933,
        70.4,
        65.067,
        64.333,
        105.067,
        65.333,
        65.3,
        64.333,
        65.633,
        68.067,
        64.6,
        66.333,
        68.933,
        86.1,
        64.833,
        66.233,
        65.933,
        66.733,
        66.167,
        68.067,
        66.1,
        66.167,
        66.633,
        66.2,
        67.867,
        73.633,
        68.667,
        67.333,
        85.667,
        67.167,
        66.3,
        65.367,
        66.3,
        65.767,
        66.9,
        53.667,
        1243.733,
        85.133,
        60.867,
        76.6
      ]
    },
    {
      "id": 31,
      "name": "Varad Dhat",
      "lapTimes": [
        39.433,
        60.133,
        63.5,
        66.667,
        68.2,
        69.433,
        64.433,
        67.1,
        64.7,
        68.0,
        69.8,
        68.3,
        72.2,
        69.967,
        70.4,
        73.333,
        72.633,
        71.933,
        67.833,
        72.067,
        72.0,
        66.7,
        70.2,
        68.8,
        68.333,
        72.533,
        73.633,
        72.933,
        74.333,
        74.7,
        75.033,
        75.967,
        77.167,
        74.733,
        75.167,
        75.733,
        75.533,
        71.767,
        70.6,
        72.867,
        73.733,
        74.633,
        72.333,
        73.133,
        71.133,
        71.367,
        70.133,
        70.433,
        71.933,
        67.867,
        66.267,
        69.867,
        283.667,
        68.7,
        70.933,
        70.2,
        69.567,
        107.1,
        124.4,
        66.8,
        66.3,
        66.333,
        126.167,
        139.2,
        62.4,
        61.167,
        61.6,
        84.633,
        103.333,
        60.733,
        57.5,
        101.233,
        61.667,
        86.033,
        63.7,
        141.0,
        88.9,
        62.533,
        107.367,
        60.867,
        100.267,
        65.5,
        79.7,
        81.067,
        65.533,
        89.333,
        119.967,
        58.7,
        90.833,
        63.5,
        79.1,
        99.767,
        83.133,
        75.067,
        105.4,
        85.1,
        83.6,
        79.2,
        95.8,
        85.6,
        62.733,
        102.267,
        87.633,
        84.967,
        78.2,
        75.167,
        85.133,
        61.067,
        75.3
      ]
    },
    {
      "id": 14,
      "name": "Oliver Flatt",
      "lapTimes": [
        40.4,
        61.4,
        63.633,
        65.767,
        67.7,
        69.167,
        64.9,
        67.133,
        70.3,
        88.533,
        69.1,
        76.833,
        72.533,
        69.133,
        67.767,
        67.1,
        97.367,
        58.667,
        62.567,
        61.9,
        116.267,
        63.2,
        62.9,
        99.7,
        75.633,
        70.1,
        69.333,
        114.367,
        58.967,
        70.133,
        91.0,
        132.433,
        60.8,
        71.6,
        69.633,
        133.633,
        58.933,
        60.733,
        206.867,
        132.3,
        125.667,
        68.767,
        76.733,
        143.333,
        60.9,
        116.8,
        98.067,
        68.833,
        110.533,
        128.367,
        135.533,
        92.2,
        64.7,
        146.6,
        124.5,
        129.467,
        122.233,
        67.533,
        102.667,
        75.133,
        85.7,
        96.6,
        57.9,
        61.867,
        90.133,
        118.867,
        61.133,
        66.967,
        94.8,
        94.9,
        69.133,
        118.7,
        107.667,
        61.267,
        100.7,
        77.067,
        71.567,
        84.533,
        80.1,
        87.7,
        95.733,
        67.933,
        105.4,
        106.4,
        116.633,
        66.433,
        64.367,
        119.433,
        118.9,
        55.933,
        75.9,
        73.7,
        110.333,
        63.067,
        201.1,
        138.7,
        115.2,
        62.967,
        92.8,
        78.867,
        95.967,
        126.267,
        66.967,
        116.533,
        64.967,
        99.233,
        70.667,
        63.8
      ]
    },
    {
      "id": 43,
      "name": "Kentrell Owens",
      "lapTimes": [
        40.833,
        63.7,
        64.833,
        65.1,
        65.133,
        69.2,
        66.6,
        63.667,
        56.433,
        57.167,
        62.2,
        68.767,
        66.933,
        67.433,
        67.5,
        67.933,
        66.567,
        66.467,
        65.267,
        64.233,
        63.267,
        64.9,
        65.6,
        67.533,
        65.767,
        63.467,
        64.867,
        66.3,
        4700.9,
        67.433,
        28.967
      ]
    },
    {
      "id": 37,
      "name": "Eric Zeng",
      "lapTimes": [
        41.2,
        63.333,
        64.833,
        65.133,
        65.1,
        69.033,
        66.767,
        62.967,
        56.5,
        56.867,
        63.267,
        68.633,
        66.933,
        67.433,
        67.5,
        67.933,
        66.567,
        66.467,
        65.267,
        64.233,
        63.267,
        64.867,
        65.633,
        67.6,
        65.8,
        63.533,
        64.7,
        66.467,
        58.167,
        65.4,
        66.367,
        66.3,
        65.933,
        67.1,
        65.033,
        65.767,
        66.467,
        66.867,
        66.233,
        67.433,
        62.7,
        63.5,
        62.9,
        63.033,
        63.333,
        66.3,
        64.6,
        64.333,
        65.9,
        66.1,
        63.1,
        64.433,
        65.167,
        64.933,
        68.233,
        67.233,
        76.533,
        71.033,
        67.933,
        65.767,
        65.2,
        66.267,
        68.033,
        67.933,
        68.333,
        67.3,
        67.433,
        66.3,
        115.633,
        193.5,
        67.267,
        67.967,
        68.733,
        69.4,
        67.833,
        70.667,
        89.633,
        69.567,
        68.167,
        67.733,
        642.767
      ]
    },
    {
      "id": 41,
      "name": "Assaf Harel",
      "lapTimes": [
        41.533,
        60.733,
        57.467,
        59.233,
        59.333,
        59.133,
        58.367,
        57.3,
        58.4,
        60.2,
        58.633,
        58.267,
        59.0,
        60.467,
        59.667,
        56.967,
        56.833,
        56.467,
        55.467,
        55.233,
        56.3,
        57.433,
        54.033,
        55.7,
        55.933,
        54.867,
        55.633,
        56.067,
        56.567,
        61.267,
        59.1,
        60.167,
        62.433,
        61.7,
        60.133,
        61.567,
        61.033,
        61.167,
        60.2,
        60.567,
        60.367,
        61.5,
        60.133,
        59.867,
        60.733,
        59.9,
        61.9,
        60.933,
        62.4,
        61.333,
        61.433,
        64.233,
        63.933,
        66.1,
        68.2,
        68.467,
        64.867,
        64.633,
        65.8,
        63.2,
        65.167
      ]
    },
    {
      "id": 11,
      "name": "Yuxuan Mei",
      "lapTimes": [
        42.233,
        74.433,
        83.9,
        85.3,
        87.7,
        82.8,
        83.033,
        88.133,
        89.0,
        91.467,
        93.267,
        93.267,
        93.1,
        93.2,
        91.033,
        92.8,
        93.067,
        93.533,
        94.8,
        93.333,
        99.5,
        98.5,
        101.533,
        87.433,
        99.667,
        100.4,
        94.8,
        99.2,
        103.6,
        98.133,
        91.567,
        93.533,
        97.933,
        98.033,
        105.767,
        105.533,
        96.9,
        96.8,
        93.633,
        96.6,
        100.733,
        103.667,
        102.833,
        100.833,
        89.7,
        97.967,
        106.967,
        106.5,
        107.967
      ]
    },
    {
      "id": 40,
      "name": "Brian Liang",
      "lapTimes": [
        42.7,
        62.567,
        65.1,
        65.367,
        64.767,
        69.1,
        66.8,
        65.667,
        69.633,
        75.6,
        78.133,
        99.567,
        124.433,
        72.8,
        106.3,
        109.267,
        82.3,
        136.1,
        141.767,
        72.633,
        79.033,
        94.4,
        155.6,
        159.2,
        157.933,
        92.333,
        70.733,
        74.133,
        75.7,
        81.6,
        92.533,
        201.867,
        157.567,
        111.433,
        182.467,
        196.1,
        121.2,
        218.133,
        173.467,
        223.233,
        169.7,
        241.2,
        71.2,
        75.767,
        76.167,
        78.867,
        80.7,
        87.033,
        88.933,
        238.467,
        172.2,
        129.233,
        129.5,
        190.267,
        118.033,
        73.167,
        174.9,
        103.533,
        121.033,
        228.3,
        168.4,
        98.9,
        60.767,
        131.967,
        96.0,
        173.533,
        107.2,
        175.4,
        184.8,
        217.767,
        191.633
      ]
    },
    {
      "id": 42,
      "name": "Huwan Peng",
      "lapTimes": [
        43.6,
        59.967,
        60.167,
        59.4,
        60.867,
        61.133,
        60.033,
        59.167,
        56.367,
        56.6,
        58.3,
        57.467,
        57.533,
        58.333,
        59.7,
        56.3,
        56.467,
        55.9,
        55.233,
        55.5,
        56.4,
        57.433,
        58.867,
        55.167,
        58.267,
        58.367,
        55.833,
        55.9,
        58.267,
        58.3,
        60.233,
        58.333,
        57.433,
        57.967,
        59.4,
        58.0,
        58.0,
        58.967,
        58.7,
        57.233,
        76.467,
        55.8,
        57.267,
        55.867,
        56.833,
        58.733,
        59.367,
        58.833,
        57.633,
        55.567,
        56.733,
        57.733,
        57.2,
        57.233,
        56.167,
        57.6,
        56.633,
        56.367,
        56.733,
        55.567,
        56.867,
        58.0,
        58.233,
        65.933,
        52.467,
        53.6,
        55.1,
        55.633,
        58.7,
        58.0,
        58.5,
        58.5,
        59.4,
        58.5,
        57.867,
        60.533,
        57.933,
        59.1,
        58.467,
        58.367,
        58.367,
        55.633,
        51.1,
        53.833,
        52.933,
        53.233,
        53.967,
        56.667,
        52.633,
        54.267,
        52.967,
        51.833,
        50.867,
        54.033,
        52.933,
        52.367,
        52.1,
        54.2,
        53.9,
        53.333,
        52.5,
        54.667,
        54.033,
        54.1,
        53.833,
        53.3,
        54.633,
        54.2,
        124.967,
        74.567,
        72.1
      ]
    },
    {
      "id": 23,
      "name": "Tracy Mallette",
      "lapTimes": [
        44.133,
        67.767,
        67.733,
        67.6,
        66.767,
        65.8,
        66.067,
        65.633,
        67.367,
        66.933,
        67.333,
        67.867,
        68.133,
        67.833,
        67.167,
        67.267,
        67.2,
        68.133,
        66.533,
        67.6,
        68.4,
        68.4,
        68.767,
        68.567,
        69.333,
        69.833,
        70.367,
        69.9,
        70.533,
        70.833,
        73.5,
        72.0,
        71.367,
        70.767,
        71.567,
        70.4,
        70.8,
        71.4,
        72.333,
        71.933,
        73.1,
        73.467,
        72.467,
        71.5,
        73.733,
        89.467,
        120.9,
        110.367,
        67.367,
        68.867,
        69.867,
        73.3,
        71.733,
        71.067,
        73.333,
        73.733,
        72.233,
        73.1,
        72.2,
        71.033,
        71.2,
        72.133,
        73.167,
        71.967,
        73.367,
        72.6,
        72.6,
        73.567,
        74.867,
        75.767,
        77.1,
        76.3,
        73.867,
        73.633,
        72.567,
        73.633,
        74.733,
        74.833,
        71.667,
        74.0,
        77.5,
        77.733,
        76.333,
        75.933,
        75.533,
        76.567,
        74.767,
        74.8,
        75.3,
        74.4,
        74.6,
        73.8,
        73.867,
        76.467,
        76.6,
        74.5,
        73.7,
        73.733,
        72.3,
        73.9,
        76.167,
        72.5,
        72.533,
        74.033,
        74.1,
        75.233,
        76.533,
        74.9,
        76.2,
        68.467
      ]
    },
    {
      "id": 24,
      "name": "Tim Mallette",
      "lapTimes": [
        44.433,
        67.467,
        67.733,
        67.6,
        66.767,
        65.7,
        66.167,
        65.667,
        67.3,
        66.967,
        67.267,
        67.933,
        68.133,
        67.833,
        67.167,
        67.267,
        67.067,
        68.267,
        66.533,
        67.6,
        68.4,
        68.4,
        68.767,
        68.567,
        69.333,
        69.833,
        70.367,
        69.7,
        70.633,
        73.767,
        71.8,
        70.867,
        71.267,
        70.8,
        71.633,
        70.4,
        70.8,
        71.4,
        72.3,
        71.967,
        72.9,
        73.5,
        72.533,
        71.533,
        78.433,
        191.533,
        59.967,
        64.567,
        67.4,
        68.8,
        70.5,
        72.667,
        71.567,
        71.233,
        73.3,
        73.767,
        72.233,
        73.133,
        72.167,
        70.833,
        71.333,
        72.067,
        73.2,
        72.133,
        73.433,
        72.467,
        72.533,
        73.7,
        74.733,
        75.9,
        77.1,
        76.233,
        73.867,
        73.6,
        72.533,
        73.767,
        74.633,
        74.933,
        71.7,
        73.967,
        77.467,
        77.767,
        76.267,
        75.867,
        75.567,
        76.567,
        74.833,
        74.733,
        75.4,
        74.333,
        74.6,
        73.8,
        73.9,
        76.5,
        76.5,
        74.5,
        73.7,
        73.767,
        72.3,
        74.333,
        75.7,
        72.4,
        72.633,
        73.967,
        73.967,
        75.367,
        76.633,
        74.867,
        76.167,
        68.5
      ]
    },
    {
      "id": 36,
      "name": "Jon Froehlich",
      "lapTimes": [
        48.433,
        69.067,
        71.567,
        69.133,
        64.2,
        63.2,
        63.7,
        63.233,
        62.3,
        60.667,
        61.167,
        60.433,
        64.133,
        66.9,
        64.3,
        67.733,
        63.533,
        64.3,
        64.467,
        65.333,
        63.067,
        63.1,
        63.633,
        64.0,
        62.7,
        62.567,
        63.4,
        64.4,
        62.967,
        59.8,
        62.8,
        60.733,
        60.233,
        62.133,
        66.667,
        63.0,
        61.1,
        63.433,
        66.933,
        69.867,
        70.067,
        60.467,
        60.967,
        62.333,
        59.133,
        60.167,
        58.533,
        60.4,
        59.233,
        60.033,
        59.167,
        59.2,
        65.233,
        59.167,
        60.3,
        59.567,
        71.133,
        64.3,
        64.433,
        60.967,
        60.233,
        62.533,
        58.433,
        58.1,
        58.2,
        58.033,
        57.333,
        55.733,
        56.067,
        55.533,
        55.867,
        55.267,
        55.7,
        55.5,
        56.2,
        56.4,
        56.967,
        57.267,
        58.0,
        57.2,
        57.467,
        57.1,
        56.933,
        58.9,
        59.533,
        57.633,
        57.8,
        57.133,
        58.6,
        59.3,
        60.267,
        57.767,
        60.133,
        67.467,
        59.9,
        59.433,
        59.133,
        58.6,
        59.233,
        58.633,
        58.3,
        57.367,
        56.4,
        56.433,
        56.467,
        57.767,
        57.833,
        56.4,
        55.867,
        54.9
      ]
    },
    {
      "id": 18,
      "name": "Maya Cakmak",
      "lapTimes": [
        48.467,
        72.567,
        89.133,
        78.433,
        78.733,
        124.967,
        77.533,
        75.667,
        78.3,
        77.3,
        77.3,
        80.433,
        84.6,
        82.433,
        80.8,
        85.767,
        81.867,
        104.767,
        226.767,
        72.133,
        142.367,
        291.1,
        75.833,
        79.867,
        82.5,
        165.733,
        273.4,
        63.533,
        154.467,
        77.8,
        82.6,
        83.467,
        83.667,
        79.467,
        94.0,
        98.933,
        91.067,
        88.267,
        91.533,
        92.667,
        102.3,
        114.567,
        199.0,
        59.433,
        71.1,
        65.8,
        70.033,
        75.0,
        78.367,
        69.767,
        77.3,
        76.233,
        76.133,
        82.267,
        73.333
      ]
    },
    {
      "id": 32,
      "name": "Anoop",
      "lapTimes": [
        50.167,
        68.867,
        61.267,
        57.0,
        59.2,
        58.233,
        59.467,
        57.967,
        58.3,
        59.1,
        58.267,
        59.8,
        56.967,
        59.767,
        60.6,
        59.767,
        59.9,
        60.0,
        59.633,
        63.4,
        60.467,
        62.7,
        62.167,
        61.533,
        63.2,
        63.667,
        65.267,
        95.133,
        62.533,
        65.833,
        65.467,
        78.467,
        66.233,
        66.467,
        66.433,
        65.733,
        67.933,
        66.067,
        67.7,
        68.767,
        70.167,
        70.133,
        71.567,
        67.867,
        70.967,
        68.167,
        70.333,
        68.967,
        69.9,
        69.733,
        71.033,
        67.3,
        128.933,
        69.867,
        74.767,
        75.3,
        71.3,
        71.533,
        72.533,
        70.767,
        73.7,
        70.567,
        75.133,
        100.9,
        72.433,
        74.133,
        72.433,
        73.033,
        73.467,
        75.2,
        156.133,
        76.8,
        74.5,
        75.9,
        77.033,
        77.267,
        76.533,
        74.033,
        76.4,
        76.333,
        78.067,
        123.333,
        73.833,
        76.5,
        76.433,
        76.367,
        76.167,
        70.467,
        73.967,
        74.0,
        77.867,
        77.0,
        76.267,
        78.833,
        76.167,
        84.833,
        128.467,
        78.2,
        116.8,
        120.433,
        83.3,
        81.233,
        80.133,
        79.533,
        81.4,
        80.467,
        110.0,
        79.667,
        77.933,
        69.033
      ]
    },
    {
      "id": 7,
      "name": "Divyansh Pareek",
      "lapTimes": [
        57.2,
        74.533,
        74.6,
        80.367,
        85.633,
        89.133,
        87.433,
        85.933,
        85.367,
        85.467,
        85.933,
        83.567,
        83.467,
        83.567,
        82.9,
        82.233,
        84.767,
        82.967,
        81.867,
        87.033,
        86.3,
        86.733,
        84.933,
        86.2,
        83.967,
        82.333,
        82.033,
        135.567,
        81.433,
        81.4,
        86.7,
        86.4,
        84.7,
        84.2,
        85.333,
        84.5,
        84.933,
        85.433,
        84.8,
        85.933,
        86.0,
        84.267,
        84.633,
        107.167,
        79.267,
        80.467,
        83.8,
        82.067,
        79.467,
        80.967,
        79.233,
        78.267,
        81.267,
        83.7,
        47.567,
        43.567,
        1848.867,
        68.033
      ]
    },
    {
      "id": 12,
      "name": "Andrey Risukhin",
      "lapTimes": [
        156.167,
        83.6,
        67.567,
        69.633,
        65.933,
        64.233,
        103.467,
        103.4,
        101.633,
        101.733,
        105.1,
        105.667,
        106.0,
        108.733,
        135.3,
        112.2,
        113.367,
        107.8,
        107.3,
        118.833,
        105.633,
        110.2,
        115.267,
        108.3,
        110.0,
        116.067,
        187.733,
        110.2,
        111.0,
        113.033,
        112.1,
        114.4,
        192.433,
        128.333,
        123.333,
        154.167,
        128.533,
        134.033,
        429.433,
        129.567,
        129.767,
        187.467,
        136.167,
        131.433,
        203.567,
        147.7,
        179.767,
        140.733,
        140.633,
        143.133,
        84.033,
        31.867,
        1141.167,
        1187.233
      ]
    },
    {
      "id": 51,
      "name": "Noah H",
      "lapTimes": [
        367.167,
        67.633,
        64.8,
        64.5,
        63.0,
        63.7,
        65.567,
        67.2,
        70.5,
        64.767,
        99.8,
        100.633,
        85.2,
        103.3,
        129.067,
        98.433,
        70.1,
        565.967,
        75.8,
        80.0,
        82.333,
        231.767,
        63.467,
        323.4,
        67.8,
        67.467,
        63.267,
        110.8,
        78.633,
        69.133,
        82.567,
        97.833,
        92.233,
        88.067,
        90.867,
        229.433,
        81.367,
        75.033,
        75.6,
        103.967,
        88.033,
        94.267,
        127.6,
        63.933
      ]
    },
    {
      "id": 45,
      "name": "Stephen Spencer",
      "lapTimes": [
        1376.667,
        80.733,
        79.933,
        78.3,
        76.833,
        77.867,
        76.9,
        76.9,
        76.2,
        76.3,
        75.933,
        74.5,
        75.867,
        72.4,
        95.733,
        74.567,
        76.6,
        75.967,
        78.067,
        78.767,
        77.667,
        77.533,
        78.067,
        77.033,
        77.2,
        75.633,
        76.8,
        77.467,
        107.133,
        74.567,
        79.533,
        75.233,
        73.7,
        75.667,
        76.567,
        76.533,
        75.767,
        74.767,
        74.733,
        73.533,
        75.233,
        75.2,
        75.667,
        74.733,
        91.633
      ]
    },
    {
      "id": 25,
      "name": "Lauren Bricker",
      "lapTimes": [
        1479.867,
        124.867,
        122.533,
        120.2,
        118.7,
        118.633,
        119.033,
        120.733,
        119.8,
        129.133,
        136.767,
        119.167,
        117.4,
        119.533,
        119.333,
        120.8,
        126.533,
        130.1,
        138.033,
        128.467,
        120.067,
        121.6,
        117.033,
        115.933,
        76.767
      ]
    },
    {
      "id": 28,
      "name": "Andrea Coladangelo",
      "lapTimes": [
        5951.233,
        71.067,
        74.267,
        64.9,
        60.067,
        65.2,
        64.8,
        56.867,
        58.733,
        62.833,
        67.167,
        64.133,
        61.133,
        63.7,
        60.567,
        62.167,
        58.4,
        61.1,
        59.9,
        69.933,
        71.067,
        66.0,
        59.867,
        57.8,
        58.033,
        59.267,
        64.267,
        56.367,
        55.333,
        58.3
      ]
    },
    {
      "id": 29,
      "name": "Jing Yu",
      "lapTimes": [
        5951.567,
        71.467,
        73.8,
        71.8,
        70.933,
        71.6,
        72.1,
        74.267,
        73.033,
        70.667,
        70.367,
        72.233,
        71.633,
        63.967,
        69.133,
        69.833,
        69.8,
        70.533,
        73.133,
        72.267,
        72.133,
        76.367,
        77.833,
        70.3,
        66.2
      ]
    }
  ]
}